gaort/Main.py
gaort/__init__.py
pypi_version_test-2.3.2.dist-info/DESCRIPTION.rst
pypi_version_test-2.3.2.dist-info/METADATA
pypi_version_test-2.3.2.dist-info/RECORD
pypi_version_test-2.3.2.dist-info/WHEEL
pypi_version_test-2.3.2.dist-info/metadata.json
pypi_version_test-2.3.2.dist-info/top_level.txt
